cds_scrapers/__init__.py
cds_scrapers/receptiviti.py
cds_scrapers-0.2.0.dist-info/WHEEL
cds_scrapers-0.2.0.dist-info/METADATA
cds_scrapers-0.2.0.dist-info/RECORD
