Metadata-Version: 2.1
Name: cds-scrapers
Version: 0.2.0
Summary: 
Author: albertomerango
Author-email: alberto.marengo@coeuraj.com
Requires-Python: >=3.9,<4.0
Classifier: Programming Language :: Python :: 3
Classifier: Programming Language :: Python :: 3.9
Classifier: Programming Language :: Python :: 3.10
Classifier: Programming Language :: Python :: 3.11
Requires-Dist: pandas (>=1.5.1,<2.0.0)
Requires-Dist: pytest (>=7.1.3,<8.0.0)
Requires-Dist: requests (>=2.28.1,<3.0.0)
Requires-Dist: textstat (>=0.7.3,<0.8.0)
